backtesting/__init__.py
backtesting/backtesting.py
backtesting/order_class.py
backtesting/positions.py
financial_backtesting-0.2.2.dist-info/licenses/LICENSE
financial_backtesting-0.2.2.dist-info/METADATA
financial_backtesting-0.2.2.dist-info/WHEEL
financial_backtesting-0.2.2.dist-info/top_level.txt
financial_backtesting-0.2.2.dist-info/RECORD
